graphframes/__init__.pyi
graphframes/_typing.pyi
graphframes/graphframe.pyi
graphframes/py.typed
graphframes/tests.pyi
graphframes/examples/__init__.pyi
graphframes/examples/belief_propagation.pyi
graphframes/examples/graphs.pyi
graphframes/lib/__init__.pyi
graphframes/lib/aggregate_messages.pyi
graphframes/lib/pregel.pyi
graphframes_stubs-0.8.0.dist-info/LICENSE
graphframes_stubs-0.8.0.dist-info/METADATA
graphframes_stubs-0.8.0.dist-info/WHEEL
graphframes_stubs-0.8.0.dist-info/top_level.txt
graphframes_stubs-0.8.0.dist-info/RECORD
